MANIFEST.in
README
setup.py
ev3dev/__init__.py
ev3dev/__init__.py.json
ev3dev/_ev3.pyd
ev3dev/_ev3.so
ev3dev/ev3.py
ev3dev/eg/README.md
ev3dev/eg/dc.py
ev3dev/eg/io.py
ev3dev/eg/led.py
ev3dev/eg/light.py
ev3dev/eg/port.py
ev3dev/eg/poweroff.py
ev3dev/eg/remote.py
ev3dev/eg/sensor.py
ev3dev/eg/tacho.py
ev3dev_c.egg-info/PKG-INFO
ev3dev_c.egg-info/SOURCES.txt
ev3dev_c.egg-info/dependency_links.txt
ev3dev_c.egg-info/not-zip-safe
ev3dev_c.egg-info/top_level.txt