Metadata-Version: 1.1
Name: ev3dev-c
Version: 1.0rc2
Summary: LEGO MINDSTORMS EV3 Debian C library + Python, Ruby and Perl wrappers
Home-page: https://github.com/in4lio/ev3dev-c
Author: Vitaly Kravtsov
Author-email: in4lio@gmail.com
License: MIT
Platform: ev3dev
Platform: windows
Classifier: Development Status :: 4 - Beta
Classifier: Environment :: Console
Classifier: Intended Audience :: Developers
Classifier: License :: OSI Approved :: MIT License
Classifier: Operating System :: Microsoft :: Windows
Classifier: Operating System :: POSIX :: Linux
Classifier: Programming Language :: Python
Classifier: Programming Language :: C
